netwatcher_cli/__init__.py
netwatcher_cli/__main__.py
netwatcher_cli/ip_api_client.py
netwatcher_cli/ip_threat_assessment.py
netwatcher_cli/logging_config.py
netwatcher_cli/main.py
netwatcher_cli/py.typed
netwatcher_cli/rconn.py
netwatcher_cli/scan.py
netwatcher_cli/ui.py
netwatcher_cli/version.py
netwatcher_cli-0.2.1.dist-info/METADATA
netwatcher_cli-0.2.1.dist-info/WHEEL
netwatcher_cli-0.2.1.dist-info/entry_points.txt
netwatcher_cli-0.2.1.dist-info/RECORD
