Metadata-Version: 2.4
Name: netwatcher-cli
Version: 0.2.1
Summary: Monitor and track active network connections
Project-URL: Documentation, https://github.com/pfischer1687/netwatcher-cli/blob/main/docs/cli.md
Project-URL: Repository, https://github.com/pfischer1687/netwatcher-cli
Project-URL: Issues, https://github.com/pfischer1687/netwatcher-cli/issues
Project-URL: Changelog, https://github.com/pfischer1687/netwatcher-cli/blob/main/CHANGELOG.md
Author-email: Paul Fischer <paulfischerdev@gmail.com>
Maintainer-email: Paul Fischer <paulfischerdev@gmail.com>
License-Expression: MIT
Keywords: CLI,Typer,monitoring,network,security
Classifier: Development Status :: 3 - Alpha
Classifier: Intended Audience :: Developers
Classifier: License :: OSI Approved :: MIT License
Classifier: Operating System :: OS Independent
Classifier: Programming Language :: Python :: 3
Requires-Python: >=3.9
Requires-Dist: click~=8.1.8
Requires-Dist: httpx~=0.28.1
Requires-Dist: loguru~=0.7.3
Requires-Dist: psutil~=7.0.0
Requires-Dist: pydantic-settings~=2.9.1
Requires-Dist: pydantic~=2.11.4
Requires-Dist: rich~=14.0.0
Requires-Dist: typer~=0.15.3
Requires-Dist: yarl~=1.20.0
